ohmyddl/__init__.py
ohmyddl/__main__.py
ohmyddl/bottle.py
ohmyddl/cachemanager.py
ohmyddl/exceptions.py
ohmyddl/models.py
ohmyddl/server.py
ohmyddl/utils.py
ohmyddl-0.1.5.dist-info/LICENSE
ohmyddl-0.1.5.dist-info/METADATA
ohmyddl-0.1.5.dist-info/WHEEL
ohmyddl-0.1.5.dist-info/entry_points.txt
ohmyddl-0.1.5.dist-info/top_level.txt
ohmyddl-0.1.5.dist-info/RECORD
