Metadata-Version: 2.1
Name: ohmyddl
Version: 0.1.5
Summary: A tool to collect deadline in SHU.
Home-page: https://github.com/hwenwur/oh-my-ddl
Author: hwenwur
Author-email: hwenwur@qq.com
License: UNKNOWN
Platform: UNKNOWN
Classifier: Programming Language :: Python :: 3
Classifier: License :: OSI Approved :: GNU General Public License (GPL)
Classifier: Operating System :: OS Independent
Requires-Python: >=3.6
Requires-Dist: lxml
Requires-Dist: requests
